deeptranslit/__init__.py
deeptranslit/deeptranslit.py
deeptranslit-1.1.1.dist-info/LICENSE
deeptranslit-1.1.1.dist-info/METADATA
deeptranslit-1.1.1.dist-info/WHEEL
deeptranslit-1.1.1.dist-info/top_level.txt
deeptranslit-1.1.1.dist-info/RECORD
